binswap/__init__.py
binswap/main.py
binswap-0.3.1.dist-info/LICENSE
binswap-0.3.1.dist-info/METADATA
binswap-0.3.1.dist-info/WHEEL
binswap-0.3.1.dist-info/entry_points.txt
binswap-0.3.1.dist-info/top_level.txt
binswap-0.3.1.dist-info/RECORD
