Metadata-Version: 2.1
Name: binswap
Version: 0.3.1
Summary: Command-line utility for Monitoring and Relaunching Executables and Scripts.
Home-page: https://github.com/Mt9555/binswap
Author: temcr
Author-email: topzydrumz@gmail.com
License: MIT
Requires-Python: >=3.6
License-File: LICENSE
Requires-Dist: watchdog
